{"assets":{"AC39498FF9F7C378AB07A39C89847DE4":{"type":"texture","index":0,"assetRequest":{"type":"slide","state":"contents","slide":"none"},"url":{"native":"assets\/72B6A524-C8A9-454B-A8CA-40FEBDC0ABDC.pdf"},"width":1920,"height":1080},"2E078BE0E7BE3D229CB5AE7D571A9EA9":{"type":"texture","index":1,"assetRequest":{"type":"slide","state":"contents","slide":"none"},"url":{"native":"assets\/72B6A524-C8A9-454B-A8CA-40FEBDC0ABDC.pdf"},"width":1920,"height":1080}},"events":[{"effects":[{"beginTime":0,"baseLayer":{"animations":[],"initialState":{"affineTransform":[1,0,0,1,0,0],"masksToBounds":false,"rotation":0,"scale":1,"position":{"pointX":960,"pointY":540},"width":1920,"sublayerTransform":[1,0,0,0,0,1,0,0,0,0,1,0,0,0,0,1],"contentsRect":{"y":0,"x":0,"width":1,"height":1},"opacity":1,"edgeAntialiasingMask":251658240,"height":1080,"hidden":false,"anchorPoint":{"pointX":0.5,"pointY":0.5}},"objectID":"0","layers":[{"animations":[],"initialState":{"affineTransform":[1,0,0,1,0,0],"masksToBounds":false,"rotation":0,"scale":1,"position":{"pointX":960,"pointY":540},"width":1920,"sublayerTransform":[1,0,0,0,0,1,0,0,0,0,1,-0.00035007912466775983,0,0,0,1],"contentsRect":{"y":0,"x":0,"width":1,"height":1},"opacity":1,"edgeAntialiasingMask":251658240,"height":1080,"hidden":false,"anchorPoint":{"pointX":0.5,"pointY":0.5}},"layers":[{"animations":[],"layers":[],"texturedRectangle":{"isBackgroundTexture":false,"singleTextureOpacity":1,"textureType":0,"textBaseline":0,"textXHeight":0,"isVerticalText":false},"initialState":{"affineTransform":[1,0,0,1,0,0],"masksToBounds":false,"rotation":0,"scale":1,"position":{"pointX":960,"pointY":540},"width":1920,"sublayerTransform":[1,0,0,0,0,1,0,0,0,0,1,0,0,0,0,1],"contentsRect":{"y":0,"x":0,"width":1,"height":1},"opacity":1,"edgeAntialiasingMask":0,"height":1080,"hidden":false,"anchorPoint":{"pointX":0.5,"pointY":0.5}},"texture":"2E078BE0E7BE3D229CB5AE7D571A9EA9"},{"animations":[{"additive":false,"timeOffset":0,"beginTime":0,"from":{"scalar":false},"repeatCount":0,"fillMode":"both","duration":0.01,"autoreverses":false,"property":"hidden","to":{"scalar":true},"removedOnCompletion":false}],"layers":[],"texturedRectangle":{"isBackgroundTexture":false,"singleTextureOpacity":1,"textureType":0,"textBaseline":0,"textXHeight":0,"isVerticalText":false},"initialState":{"affineTransform":[1,0,0,1,0,0],"masksToBounds":false,"rotation":0,"scale":1,"position":{"pointX":960,"pointY":540},"width":1920,"sublayerTransform":[1,0,0,0,0,1,0,0,0,0,1,0,0,0,0,1],"contentsRect":{"y":0,"x":0,"width":1,"height":1},"opacity":1,"edgeAntialiasingMask":0,"height":1080,"hidden":false,"anchorPoint":{"pointX":0.5,"pointY":0.5}},"texture":"AC39498FF9F7C378AB07A39C89847DE4"}]}]},"effects":[],"duration":0.01,"type":"transition","attributes":{"direction":0},"name":"none","objectID":"0"}],"automaticPlay":false,"hyperlinks":[],"accessibility":[{"text":"Frühlingsmüdigkeit","targetRectangle":{"y":76.793403625488281,"x":975.90871260048038,"width":810.03239875076042,"height":107}},{"text":"Si la religion n’est plus une solution, la foi est remise à l’épreuve à chaque changement de saison.  La nature change et nous avons le sentiment de rester les mêmes, bloqués en hiver. Le printemps apporte son lot de mélancolie. Quête spirituelle sans être religieuse, la mode affirme la beauté du geste de se délier. En témoigne le ruban rose enroulé autour du bras droit, qui n’est pas noué mais ondule librement, comme une caresse au vent. ","targetRectangle":{"y":227.10767650604248,"x":1101.702392578125,"width":696.6771850585942,"height":226.80000901222229}},{"text":"Le printemps comme l’automne est un deuil. Le corps doit se réajuster, l’être doit renoncer à tout ce qu’il n’a pas été en hiver, et qu’il ne pourra plus être avant l’hiver prochain. Il doit accepter d’être pendant quelques temps une feuille morte. C’est ainsi qu’il pourra redevenir page blanche et voir s’épanouir les fleurs du temps à même la peau. La feuille morte est ici représentée par un plastron, col montant mi-maille, mi soie, aux nervures hétéroclites (zip, rainures de la maille, fils de soie sauvage). Elle apparaît dans sa force crépusculaire et régénératrice. Les mitaines en maille jaune rappellent ces nervures, de même que le pantalon rayé rouge et blanc.","targetRectangle":{"y":486.3076868057251,"x":1101.702392578125,"width":696.6771850585942,"height":324.00001287460327}},{"text":"La honte originelle est imprimée noir sur blanc sur la culotte du modèle. Motif ancestral, question fondamentale qui se repose dès que des corps se dénudent autour de soi ; pourquoi se cacher ? Pourquoi serait-il plus éthique d’apparaître habillé en société, que nu ?","targetRectangle":{"y":842.7077009677887,"x":1101.702392578125,"width":696.6771850585942,"height":129.60000514984131}},{"text":"pasted-image.jpeg","targetRectangle":{"y":7.3524120125512127e-10,"x":-2.5620619226174313e-07,"width":1440,"height":1080}}],"baseLayer":{"animations":[],"initialState":{"affineTransform":[1,0,0,1,0,0],"masksToBounds":false,"rotation":0,"scale":1,"position":{"pointX":960,"pointY":540},"width":1920,"sublayerTransform":[1,0,0,0,0,1,0,0,0,0,1,0,0,0,0,1],"contentsRect":{"y":0,"x":0,"width":1,"height":1},"opacity":1,"edgeAntialiasingMask":251658240,"height":1080,"hidden":false,"anchorPoint":{"pointX":0.5,"pointY":0.5}},"objectID":"0","layers":[{"animations":[],"initialState":{"affineTransform":[1,0,0,1,0,0],"masksToBounds":false,"rotation":0,"scale":1,"position":{"pointX":960,"pointY":540},"width":1920,"sublayerTransform":[1,0,0,0,0,1,0,0,0,0,1,-0.00035007912466775983,0,0,0,1],"contentsRect":{"y":0,"x":0,"width":1,"height":1},"opacity":1,"edgeAntialiasingMask":251658240,"height":1080,"hidden":false,"anchorPoint":{"pointX":0.5,"pointY":0.5}},"layers":[{"animations":[],"layers":[],"texturedRectangle":{"isBackgroundTexture":false,"singleTextureOpacity":1,"textureType":0,"textBaseline":0,"textXHeight":0,"isVerticalText":false},"initialState":{"affineTransform":[1,0,0,1,0,0],"masksToBounds":false,"rotation":0,"scale":1,"position":{"pointX":960,"pointY":540},"width":1920,"sublayerTransform":[1,0,0,0,0,1,0,0,0,0,1,0,0,0,0,1],"contentsRect":{"y":0,"x":0,"width":1,"height":1},"opacity":1,"edgeAntialiasingMask":0,"height":1080,"hidden":false,"anchorPoint":{"pointX":0.5,"pointY":0.5}},"texture":"AC39498FF9F7C378AB07A39C89847DE4"}]}]}}]}